Workbook

Sheet Summary
A1: Straddle Dart — BOM summary, rev 7 (riveted aluminum hull)
A2: Totals pull from the three BOM tabs. Change quantities, prices or weights there; change the contingency in B11.
A4: Group | B4: Est. cost ($) | C4: Weight (lb) | D4: Weight in CAD (lb) | E4: Weight not in CAD (lb)
A5: Hull | B5: =Hull!F25 | C5: =Hull!G25 | D5: =Hull!G26 | E5: =Hull!G27
A6: Drivetrain | B6: =Drivetrain!F41 | C6: =Drivetrain!G41 | D6: =Drivetrain!G42 | E6: =Drivetrain!G43
A7: Everything else | B7: ='Everything else'!F102 | C7: ='Everything else'!G102 | D7: ='Everything else'!G103 | E7: ='Everything else'!G104
A8: Subtotal | B8: =SUM(B5:B7) | C8: =SUM(C5:C7) | D8: =SUM(D5:D7) | E8: =SUM(E5:E7)
A10: Contingency (shipping, tax, mistakes, extras) | B10: =B8*B11
A11: Contingency rate | B11: 0.15 | C11: Assumption: 15% of materials; edit as needed
A12: Estimated materials total | B12: =B8+B10
A14: Weight check
A15: Empty boat, CAD model (no fuel or crew) | B15: 1160 | C15: lb, rev 7 estimate: rev 6 trim analysis (1,038.8) plus the rev 7 changes in this workbook
A16: BOM weight in CAD (should match) | B16: =D8
A17: Difference | B17: =B16-B15
A18: Empty boat incl. items not in CAD | B18: =C8
A20: Labor and the fab shop shear/brake service are not included here; see DIY-Mini-Airboat_Build-Guide_Aluminum.xlsx.
A21: Supplier links appear only where a supplier was discussed during design.

Sheet Hull
A1: Straddle Dart — Hull BOM (riveted aluminum) (rev 7)
A2: Costs are 2026 USD estimates. Blue cells are inputs you can change; Est. cost = Qty x Unit cost. Weight is the installed line weight in lb.
A4: Item | B4: Use / spec | C4: Qty | D4: Unit | E4: Unit cost ($) | F4: Est. cost ($) | G4: Weight (lb) | H4: In CAD weight? | I4: Supplier link | J4: Notes
A5: 5052-H32 aluminum sheet 0.125 in, 60 x 144 in | B5: Bottom halves with the 3 in chine bent in, bow rocker pieces, bow face | C5: 3 | D5: sheet | E5: 625 | F5: =C5*E5 | G5: 135.6 | H5: Y | J5: Was 0.090: ISO 12215-5 check (Structural Checks 8c). Centerline seam over the center stringer; transverse butt seam with doubler at frame 120
A6: 5052-H32 aluminum sheet 0.063 in, 48 x 144 in | B6: Side panels | C6: 2 | D6: sheet | E6: 230 | F6: =C6*E6 | G6: 22 | H6: Y
A7: 5052-H32 aluminum sheet 0.125 in, 24 x 72 in | B7: Transom | C7: 1 | D7: sheet | E7: 180 | F7: =C7*E7 | G7: 14.5 | H7: Y
A8: 5052 strip 0.080 and 0.063 in, brake-formed into hat sections | B8: 5 stringers, 2.5 in tall (0.080 for the two engine-bed stringers); 1 in cross-drain slot in each at x 3.5-4.5 | C8: 1 | D8: lot | E8: 350 | F8: =C8*E8 | G8: 39.4 | H8: Y | J8: Bend to the rocker before riveting
A9: 6061 angle 1-1/2 x 1-1/2 x 1/8 in, 12 ft | B9: 10 frames (x 12, 24, 36, 48, 60, 72, 84, 96, 111.5, 120 in) + transom frame | C9: 7 | D9: stick | E9: 42 | F9: =C9*E9 | G9: 38.9 | H9: Y | J9: Frames at 60, 84 and 111.5 in added for the 0.125 bottom (ISO 12215-5). 1 x 3/4 in limber notch at the skin in every bay of every frame; deburr and prime the cut edges
A10: 6061 rectangular tube 2 x 3 x 1/8 in, 12 ft | B10: Engine-bed box beams on the bed stringers | C10: 1 | D10: stick | E10: 95 | F10: =C10*E10 | G10: 12.9 | H10: Y
A11: 6061 angle 1 x 1 x 1/8 in, 12 ft | B11: Rub rails / sheer clamps | C11: 3 | D11: stick | E11: 25 | F11: =C11*E11 | G11: 6.4 | H11: Y
A12: 6061 plate 1/4 in | B12: Quarter knees and frame-12 gussets under the cage plates | C12: 1 | D12: lot | E12: 40 | F12: =C12*E12 | G12: 3.6 | H12: Y
A13: 6061 aluminum 1/4 in flat bar and plate | B13: Engine bed plates 48 x 3 in (2), cage mount plates 4 x 4 in (4) | C13: 1 | D13: lot | E13: 130 | F13: =C13*E13 | G13: 8.4 | H13: Y | J13: Drill beds 16 x 13/32 in at 3 in spacing
A14: HDPE sheet 1/8 in, 12 x 24 in | B14: Isolator strips under all aluminum plates | C14: 1 | D14: sheet | E14: 25 | F14: =C14*E14 | G14: 1.5 | H14: Y
A15: 5052-H32 sheet 1/8 in: two chine guards brake-formed to 135 deg (12.5 ft) + bent nose cap | B15: Chine guard angles opened to 135 deg; bent nose cap | C15: 1 | D15: lot | E15: 90 | F15: =C15*E15 | G15: 15.9 | H15: Y | J15: Guards brake-formed at the shop with the chine bends (were 6061 angles opened to 135 deg by hand)
A16: UHMW 1/4 in sheet, 48 x 120 in | B16: 4 bottom strips (splice over a frame) | C16: 3 | D16: sheet | E16: 290 | F16: =C16*E16 | G16: 82.8 | H16: Y | J16: 3/16 in saves about 21 lb
A17: Closed-end aluminum blind rivets 3/16 in (5052/5056, aluminum mandrel) | B17: All skin laps and framing; double rows at about 3/4 in | C17: 2400 | D17: ea | E17: 0.15 | F17: =C17*E17 | G17: 4.8 | H17: N | J17: Double rows: 3/4 in pitch on the bottom seams and chine laps, 1 in on laps above the waterline. Never open-end or steel-mandrel rivets
A18: Seam sealant (Sikaflex 291 or 3M 4200), 10 oz tubes | B18: Wet in every lap before riveting | C18: 10 | D18: tube | E18: 15 | F18: =C18*E18 | G18: 4 | H18: N
A19: SS 1/4 in through-bolts, nylock nuts, sealing washers | B19: UHMW strips through the bottom into the stringers | C19: 200 | D19: set | E19: 0.8 | F19: =C19*E19 | G19: 3 | H19: N | J19: Bed in sealant; Tef-Gel on threads
A20: Clecos 3/16 in (100) + pliers, drill bits, deburr tools | B20: Tooling | C20: 1 | D20: lot | E20: 150 | F20: =C20*E20 | G20: 0 | H20: N
A21: Self-etching primer | B21: Faying surfaces and cut edges only; the hull stays bare 5052 (topcoat optional later) | C21: 1 | D21: lot | E21: 60 | F21: =C21*E21 | G21: 1 | H21: N
A22: Rev 6 joint details
A23: Bed plates lengthened to 52 in, new 10-hole pattern; knees/gussets drilled for cage-foot bolts | B23: Net change from the detailed hull model | C23: 1 | D23: lot | E23: 40 | F23: =C23*E23 | G23: 0.7 | H23: Y | J23: Hole positions in the fab workbook
A25: Total | F25: =SUM(F5:F23) | G25: =SUM(G5:G23)
A26: Weight included in the CAD model | G26: =SUMIF(H5:H23,"Y",G5:G23)
A27: Weight not in the CAD model (fasteners, paint, wiring) | G27: =SUMIF(H5:H23,"N",G5:G23)
A28: CAD model weight for this group (reference) | G28: 330.5 | J28: From the CAD weight reports (hull r4.2, drivetrain r5, layout r6 + cage r2 + flotation r5)

Sheet Drivetrain
A1: Straddle Dart — Drivetrain BOM (rev 7)
A2: Costs are 2026 USD estimates. Blue cells are inputs you can change; Est. cost = Qty x Unit cost. Weight is the installed line weight in lb.
A4: Item | B4: Use / spec | C4: Qty | D4: Unit | E4: Unit cost ($) | F4: Est. cost ($) | G4: Weight (lb) | H4: In CAD weight? | I4: Supplier link | J4: Notes
A5: Suzuki G13B 1.3 L DOHC 16-valve engine, dressed | B5: 1989-94 Suzuki Swift GT/GTi (US) or a JDM Cultus GT-i import; with flywheel, starter, alternator, intake, ECU and harness | C5: 1 | D5: ea | E5: 1200 | F5: =C5*E5 | G5: 194 | H5: Y | I5: https://www.car-part.com | J5: About 100 hp at 6,500 rpm, about 83 lb-ft. Weight is the CAD placeholder + 15 lb for the twin-cam head: verify weight and head clearances on the engine bought
A6: Engine refresh kit | B6: Gaskets, timing belt + tensioner, water pump, plugs, thermostat, oil and filter | C6: 1 | D6: kit | E6: 320 | F6: =C6*E6 | G6: 0 | H6: N
A7: Fuel delivery | B7: Electric pump, filter, fuel line, primer bulb, clamps | C7: 1 | D7: lot | E7: 140 | F7: =C7*E7 | G7: 3 | H7: N
A8: Bellhousing adapter | B8: 3/8 in 6061 plate + shroud, machined to the G13-family pattern (G13B), starter boss | C8: 1 | D8: ea | E8: 160 | F8: =C8*E8 | G8: 11 | H8: Y | J8: Material + DIY machining; pattern from the real block
A9: Flex coupling (jaw or donut type) | B9: Torsional damper, flywheel to jackshaft; rated 150 lb-ft or more | C9: 1 | D9: ea | E9: 130 | F9: =C9*E9 | G9: 1.3 | H9: Y
A10: Jackshaft 1-1/4 in 4140 + 2 bearings + housing | B10: Takes belt pull off the crankshaft | C10: 1 | D10: lot | E10: 170 | F10: =C10*E10 | G10: 4.4 | H10: Y
A11: HTD 8M pulley, 30 teeth, 85 mm, taper-lock + bushing | B11: Drive pulley on jackshaft | C11: 1 | D11: ea | E11: 140 | F11: =C11*E11 | G11: 5.7 | H11: Y
A12: HTD 8M pulley, 75 teeth, 85 mm, aluminum, taper-lock + bushing | B12: Prop pulley between the bearings | C12: 1 | D12: ea | E12: 330 | F12: =C12*E12 | G12: 7.5 | H12: Y
A13: HTD belt 2320-8M-85 (290 teeth) | B13: Gates PowerGrip HTD or equal; 2.5 : 1 | C13: 1 | D13: ea | E13: 190 | F13: =C13*E13 | G13: 3 | H13: Y | J13: Confirm width with Gates design data for the G13B (83 lb-ft, 6,500 rpm); may need a wider HTD belt or Poly Chain GT Carbon
A14: Backside idler 3.5 in + bearing + pad bracket (optional) | B14: Slack-side idler bolted to adapter | C14: 1 | D14: ea | E14: 70 | F14: =C14*E14 | G14: 3.2 | H14: Y | J14: Fit only if ground runs show belt flap
A15: Prop shaft 1-1/2 in 4140 pre-hardened (28-32 HRC), 20 in, keyed | B15: Supported fore and aft | C15: 1 | D15: ea | E15: 140 | F15: =C15*E15 | G15: 9.8 | H15: Y | J15: Pre-hardened for gyroscopic bending in hard turns; carry thrust on a shoulder or clamped collar, not set screws alone
A16: Flange bearing 1-1/2 in, 4-bolt | B16: One in each yoke plate | C16: 2 | D16: ea | E16: 55 | F16: =C16*E16 | G16: 9 | H16: Y
A17: Prop flange / hub adapter | B17: Machined to the Warp Drive HPL hub pattern | C17: 1 | D17: ea | E17: 140 | F17: =C17*E17 | G17: 3.8 | H17: Y
A18: Tension yoke: 3/8 in 6061 plates + 1 in tie tubes | B18: Carries both bearings; pivots as one piece | C18: 1 | D18: lot | E18: 170 | F18: =C18*E18 | G18: 13.3 | H18: Y
A19: 1/2 in grade 8 bolts + lock nuts; 1/2-13 jack screw + block | B19: Pivot (2), arc slot (4), jack screw | C19: 1 | D19: lot | E19: 45 | F19: =C19*E19 | G19: 2 | H19: Y
A20: 6061 square tube 2 x 2 x 1/8 in | B20: A-frame legs and aft crossbar | C20: 17 | D20: ft | E20: 9 | F20: =C20*E20 | G20: 16.1 | H20: Y
A21: 6061 plate 3/8 in, 24 x 30 in | B21: Two gusset-shaped peak plates with lightening holes | C21: 1 | D21: ea | E21: 210 | F21: =C21*E21 | G21: 20 | H21: Y
A22: 6061 plate 1/4 in | B22: A-frame and brace feet (6) | C22: 1 | D22: lot | E22: 40 | F22: =C22*E22 | G22: 2.6 | H22: Y
A23: 6061 tube 1-1/2 x 1-1/2 x 1/8 and 1 x 1 in | B23: Diagonal braces (2) and adapter tie struts (2) | C23: 16 | D23: ft | E23: 8 | F23: =C23*E23 | G23: 7.1 | H23: Y
A24: Engine mount: steel bracket + polyurethane bushing | B24: Bolted to engine-bed plates at x = 30 and 42 in | C24: 4 | D24: ea | E24: 35 | F24: =C24*E24 | G24: 15.3 | H24: Y
A25: Warp Drive 64R-TX-HPL3 propeller | B25: 64 in, 3 carbon blades, HPL hub, ground-adjustable, R rotation | C25: 1 | D25: ea | E25: 1395 | F25: =C25*E25 | G25: 18 | H25: Y | I25: https://warpdriveinc.com/product/3-bld-prop-hpl-hub/ | J25: Price from Warp Drive page; confirm rotation, hub pattern and weight before ordering. G13B: pitch for 6,000-6,300 rpm at full throttle standing still
A26: Leading-edge protection tape (stoneguard) | B26: Blade leading edges | C26: 1 | D26: kit | E26: 60 | F26: =C26*E26 | G26: 0 | H26: N | J26: Warp Drive's nickel edge is the $390 alternative
A27: Honda Civic radiator (junkyard) + hoses, clamps, coolant, overflow bottle | B27: Above the hub, in front of the prop | C27: 1 | D27: lot | E27: 140 | F27: =C27*E27 | G27: 20 | H27: Y | J27: Civic radiator suits engines of about 100 hp; watch coolant temperature on a long static run
A28: Radiator cradle rails + straps | B28: On the peak plates | C28: 1 | D28: lot | E28: 35 | F28: =C28*E28 | G28: 0.8 | H28: Y
A29: Exhaust: mandrel bends, flex section, muffler, wrap, heat shields | B29: Low starboard; tailpipe over transom below the prop disk | C29: 1 | D29: lot | E29: 280 | F29: =C29*E29 | G29: 16 | H29: Y
A30: Throttle cable + return spring | B30: Pedal to throttle body | C30: 1 | D30: lot | E30: 60 | F30: =C30*E30 | G30: 1 | H30: N
A31: Rev 6 joint details
A32: A-frame details: slotted leg tops, 1/8 caps, foot gussets, mitred crossbars | B32: 6061 drops; TIG | C32: 1 | D32: lot | E32: 60 | F32: =C32*E32 | G32: 0 | H32: Y | J32: Weight included in the A-frame line below
A33: Brace clevises: 1/4 tongues and tab pairs, 3/8 grade 8 bolts + nylocks (4) | B33: Removable braces | C33: 1 | D33: lot | E33: 45 | F33: =C33*E33 | G33: 0 | H33: Y
A34: Tie-strut tabs + 5/16 bolts (4) | B34: Adapter to crossbar | C34: 1 | D34: lot | E34: 20 | F34: =C34*E34 | G34: 0 | H34: Y
A35: Engine mounts: 6061 cradles (4), steel engine-side brackets (4), DOM sleeves, poly bushings 1.75 OD x 1/2 ID (4), 1/2 grade 8 through-bolts (4) | B35: Engine-side holes to suit the real block | C35: 1 | D35: lot | E35: 160 | F35: =C35*E35 | G35: 0 | H35: Y | J35: Measure the G13B mount bosses before drilling the engine-side brackets
A36: Radiator: lower angle, 2 rubber grommets, 2 x 3/8 top stays with rubber bushings | C36: 1 | D36: lot | E36: 45 | F36: =C36*E36 | G36: 0 | H36: Y
A37: Exhaust: flex section, 2 rubber isolators, 2 SS band clamps, 6061 hanger brackets, tailpipe saddle + pad | C37: 1 | D37: lot | E37: 95 | F37: =C37*E37 | G37: 0 | H37: Y
A38: Bed-plate bolts 3/8 SS + nylocks + Tef-Gel (20) | B38: All feet and pads | C38: 20 | D38: ea | E38: 1.5 | F38: =C38*E38 | G38: 0 | H38: Y
A39: Net weight of the rev 6 drivetrain details (CAD) | B39: Reconciles to the detailed drivetrain model | C39: 1 | D39: lot | E39: 0 | F39: =C39*E39 | G39: 14.8 | H39: Y
A41: Total | F41: =SUM(F5:F39) | G41: =SUM(G5:G39)
A42: Weight included in the CAD model | G42: =SUMIF(H5:H39,"Y",G5:G39)
A43: Weight not in the CAD model (fasteners, paint, wiring) | G43: =SUMIF(H5:H39,"N",G5:G39)
A44: CAD model weight for this group (reference) | G44: 385.4 | J44: From the CAD weight reports (hull r4.2, drivetrain r5, layout r6 + cage r2 + flotation r5)

Sheet Everything else
A1: Straddle Dart — Everything else BOM: cage, rudders, steering, seating, controls, flotation, electrical, safety (rev 7)
A2: Costs are 2026 USD estimates. Blue cells are inputs you can change; Est. cost = Qty x Unit cost. Weight is the installed line weight in lb.
A4: Item | B4: Use / spec | C4: Qty | D4: Unit | E4: Unit cost ($) | F4: Est. cost ($) | G4: Weight (lb) | H4: In CAD weight? | I4: Supplier link | J4: Notes
A5: Prop cage
A6: Steel DOM tube 1 in x 0.083 in (yield 50 ksi or better) | B6: Two cage hoops, 72.4 in dia (about 19 ft each) | C6: 40 | D6: ft | E6: 6 | F6: =C6*E6 | G6: 30.9 | H6: Y | J6: Was 1 x .049: the hoops carry rudder, steering and screen loads in bending (Structural Checks)
A7: Tube rolling service | B7: Roll two 72.4 in DOM hoops | C7: 1 | D7: job | E7: 150 | F7: =C7*E7 | G7: 0 | H7: Y | J7: Muffler or fab shop
A8: Steel DOM tube 1 in x 0.065 in (yield 50 ksi or better) | B8: Cage legs, base rails, rudder rails, 8 longitudinals, aft screen bars, 2 side-bay diagonals | C8: 46 | D8: ft | E8: 5 | F8: =C8*E8 | G8: 29.8 | H8: Y | J8: Longitudinals and aft bars were EMT; diagonals added (Structural Checks)
A9: EMT conduit 1/2 in, 10 ft sticks | B9: Front screen bars (2) | C9: 2 | D9: stick | E9: 10 | F9: =C9*E9 | G9: 3.3 | H9: Y | J9: Grind off zinc before welding; ventilate
A10: Hardware cloth 1/2 in, 19 ga galvanized, 36 in x 50 ft | B10: Front, aft and side screens | C10: 1 | D10: roll | E10: 120 | F10: =C10*E10 | G10: 17.3 | H10: Y | J10: Keep 4.7 in or more from any moving part
A11: Shaft guard sleeve | B11: Fixed sleeve where the shaft passes the front screen | C11: 1 | D11: ea | E11: 15 | F11: =C11*E11 | G11: 0.2 | H11: Y
A12: Welding wire, gas, paint for cage | C12: 1 | D12: lot | E12: 120 | F12: =C12*E12 | G12: 0 | H12: N
A13: Rudders and steering
A14: Aluminum honeycomb panel 20 mm, 4 x 8 ft | B14: Two rudders 14 x 44 in | C14: 1 | D14: sheet | E14: 380 | F14: =C14*E14 | G14: 11.9 | H14: Y | I14: https://www.chalcoaluminum.com/knowledge/sandwich-panel/#Honeycomb | J14: Price is an estimate; request a quote
A15: Aluminum U-channel 3/4 in, hinge tube 1 in x 0.083 in, horns | B15: Rudder edges and hinges; seal all edges | C15: 1 | D15: lot | E15: 90 | F15: =C15*E15 | G15: 5.6 | H15: Y
A16: Hinge brackets and bushings | B16: On the 1 in rudder rails | C16: 4 | D16: ea | E16: 10 | F16: =C16*E16 | G16: 0 | H16: N
A17: Steering linkage: 2 aft horns, tie bar and drive link (5/8 x .065 steel, 4 rod ends), bellcrank (1/4 steel, 3.5 / 4 in arms) on a 3/8 x 1.5 steel bracket welded to the aft hoop, 1 x .065 DOM long rod (8.5 ft) with 2 rod ends, 3/8 SS pins | B17: Rudders to the left-hand steering lever; every link straight and pinned at both ends | C17: 1 | D17: lot | E17: 190 | F17: =C17*E17 | G17: 8.8 | H17: Y | J17: Replaces the dog-legged pushrod, which would have bent (Structural Checks, finding 1); notch the aft screen mesh round the bracket
A18: Seating, controls, fuel, battery
A19: Marine plywood 3/8 in, 4x8 | B19: Floor, transom to x = 121 in, 64 in wide | C19: 5 | D19: sheet | E19: 110 | F19: =C19*E19 | G19: 61.7 | H19: Y | J19: Bolt-down panels resting on the stringer tops (aft panel included); 6.5 in cutouts for deck plates
A20: Marine plywood 1/2 in, 4x8 | B20: Straddle bench box and bow shelf | C20: 1 | D20: sheet | E20: 150 | F20: =C20*E20 | G20: 33.3 | H20: Y
A21: Bench lids and seals: Al ledge ring + EPDM gasket + 6 SS bolts into clip nuts (battery bay); 2 SS hinges, 2 locking lid stays, rubber T-latch, 1 in drain plug (cooler) | B21: Sealed battery bay forward; gasketed dry storage / cooler aft | C21: 1 | D21: lot | E21: 160 | F21: =C21*E21 | G21: 4 | H21: Y | J21: Cooler lid hinges on the starboard top corner, opens about 95 deg
A22: Seat foam + marine vinyl | B22: Three cushions: driver (removable, over the battery lid), passenger (on the cooler lid), aft fixed | C22: 1 | D22: lot | E22: 170 | F22: =C22*E22 | G22: 4 | H22: Y
A23: Removable backrests | B23: Driver and passenger | C23: 2 | D23: ea | E23: 55 | F23: =C23*E23 | G23: 10 | H23: Y
A24: Passenger grab handles | B24: Both sides of the bench; loop 10.5 in off centre, top bar 20 in up (clears the cooler lid) | C24: 2 | D24: ea | E24: 22 | F24: =C24*E24 | G24: 3 | H24: Y
A25: Expanded-metal engine guard | B25: Between passenger and engine front | C25: 1 | D25: ea | E25: 60 | F25: =C25*E25 | G25: 5 | H25: Y
A26: Footrest, two foot ladders (6061 solid 1 in rod, welded) | B26: Left rails 7.5 and 12.5 in to port, right rails 7.5 and 14.5 in to starboard; 5 rungs each at x 105.5-117.5 in, rising 22.7 deg to the bow shelf; 8 foot plates 3/16 | C26: 1 | D26: ea | E26: 70 | F26: =C26*E26 | G26: 6.5 | H26: Y | J26: A landing for each foot like motorcycle pegs; the throttle pedal clamps to any right-ladder rung
A27: Throttle pedal assembly, rung-mounted | B27: Clamps to any rung of the right foot ladder (centred 10.75 in to starboard); cable arm, torsion return spring, rest stop | C27: 1 | D27: ea | E27: 75 | F27: =C27*E27 | G27: 2.2 | H27: Y | J27: Rung 3 suits an average adult
A28: Steering lever + pivot | B28: Port side, left hand; 1.5 in outboard of the original position (clear of the left knee) | C28: 1 | D28: ea | E28: 70 | F28: =C28*E28 | G28: 7 | H28: Y
A29: Padded grab bar | B29: Starboard, right hand at 42 in | C29: 0 | D29: ea | E29: 55 | F29: =C29*E29 | G29: 0 | H29: Y | J29: Replaced by the rev 7 driver station (see below)
A30: Portable fuel tank 6.6 gal + fuel line and primer bulb | B30: Strapped on the bow shelf | C30: 1 | D30: lot | E30: 120 | F30: =C30*E30 | G30: 4.5 | H30: Y | J30: Fuel itself (40 lb full) not counted
A31: Battery, Group 31 AGM about 100 Ah, dual purpose + tray and strap | B31: Battery bay at the front of the bench, under the driver | C31: 1 | D31: ea | E31: 300 | F31: =C31*E31 | G31: 68 | H31: Y | J31: Sealed AGM; reserve for the 12 V outlet with the engine off
A32: Adjustable trim tab (DIY aluminum) | B32: 18 x 6 in, starboard half of transom | C32: 1 | D32: ea | E32: 60 | F32: =C32*E32 | G32: 4 | H32: Y
A33: Flotation, sump, pump
A34: Two-part pour foam, 2 lb/cu ft closed-cell urethane, about 8 cu ft per kit | B34: 24 removable blocks: thin blocks under the floor aft of x = 72 in (5.1 cu ft) and under the bow shelf (4.4 cu ft), poured in molds or in each bay on a release-lined tray | C34: 2 | D34: kit | E34: 115 | F34: =C34*E34 | G34: 19 | H34: Y | J34: Urethane only (gasoline resistant); nothing bonded to the aluminum
A35: Coroplast 4 mm 4 x 8 sheets + polyurea or epoxy seal coat | B35: Bottom tray and sealed skin on every block | C35: 1 | D35: lot | E35: 100 | F35: =C35*E35 | G35: 3.7 | H35: Y | J35: Sealed skin slows water uptake
A36: HDPE sheet 1/2 in, 12 x 24 in | B36: 54 spacer pads 1.5 x 1.5 in, glued to block bottoms (1/2 in drained channel) | C36: 1 | D36: sheet | E36: 35 | F36: =C36*E36 | G36: 2.1 | H36: Y
A37: Two-part pour foam kit + covers and straps | B37: Removable side blocks (6.4 cu ft), molded to fit; they give the swamped boat its stability | C37: 1 | D37: lot | E37: 215 | F37: =C37*E37 | G37: 12.8 | H37: Y | J37: Must be strapped in whenever the boat is used
A38: Screw-out deck plates, 6 in | B38: Inspection ports in the floor (8) | C38: 8 | D38: ea | E38: 14 | F38: =C38*E38 | G38: 3.6 | H38: Y | J38: Plastic, gasketed
A39: FRP grating panel, 1 in, made into a raised box | B39: Removable grate box over the open sump (pump is taller than the low floor) | C39: 1 | D39: ea | E39: 60 | F39: =C39*E39 | G39: 2.5 | H39: Y
A40: Automatic bilge pump about 1,100 gph + float switch | B40: In the open transom sump | C40: 1 | D40: ea | E40: 90 | F40: =C40*E40 | G40: 2.5 | H40: Y
A41: Through-hull, discharge hose, clamps | B41: Discharge at 14 in on the transom | C41: 1 | D41: lot | E41: 35 | F41: =C41*E41 | G41: 1 | H41: Y
A42: Transom self-bailer with check valve, 1.5 in | B42: Bottom of sump | C42: 1 | D42: ea | E42: 45 | F42: =C42*E42 | G42: 0.5 | H42: Y | J42: Must have a working check valve
A43: Transom drain plug, 1 in (plastic or aluminum) | B43: Lowest point of the sump; pull on the trailer after every trip | C43: 1 | D43: ea | E43: 12 | F43: =C43*E43 | G43: 0.2 | H43: Y | J43: Not brass (galvanic)
A44: Pump cycle counter or hour meter on the float-switch circuit | B44: Leak early warning | C44: 1 | D44: ea | E44: 25 | F44: =C44*E44 | G44: 0 | H44: N
A45: Waterproof bilge switch (auto / off / manual), fused | B45: On the transom top, reachable from the water when the boat is swamped | C45: 1 | D45: ea | E45: 35 | F45: =C45*E45 | G45: 0 | H45: N | J45: Pump runs from the battery inside the sealed bench
A46: Floor fasteners: SS screws into rivnuts + closed-cell gasket tape | B46: Bolt-down floor panels (hold the blocks down when swamped) | C46: 1 | D46: lot | E46: 60 | F46: =C46*E46 | G46: 0 | H46: N
A47: Electrical and safety
A48: Terminals, adhesive heat shrink, cushion clamps, zip ties | C48: 1 | D48: lot | E48: 80 | F48: =C48*E48 | G48: 5 | H48: N | J48: Wire itself is itemised in the rev 7 electrical lines
A49: Dash instruments: electric tach 3-3/8 in, water temp and fuel gauges 2-1/16 in, key switch, red trouble light, lanyard kill switch | C49: 1 | D49: lot | E49: 250 | F49: =C49*E49 | G49: 3.3 | H49: Y
A50: Navigation lights (sidelights + all-round white) | B50: Needed for night running | C50: 1 | D50: set | E50: 90 | F50: =C50*E50 | G50: 2 | H50: N
A51: Safety gear: 2 PFDs, throwable cushion | B51: Carried gear | C51: 1 | D51: lot | E51: 160 | F51: =C51*E51 | G51: 0 | H51: N | J51: Not counted in boat weight; extinguisher and horn are listed in rev 7
A52: Registration and title fees | C52: 1 | D52: lot | E52: 75 | F52: =C52*E52 | G52: 0 | H52: N | J52: Estimate; check your state's rules
A53: Rev 6 joint details
A54: Cage feet: 1/4 steel pads drilled, HDPE isolators, 3/8 SS bolts (16) | B54: Bolted through the hull plates and knees | C54: 1 | D54: lot | E54: 70 | F54: =C54*E54 | G54: 0 | H54: Y
A55: Rudder pivots: 1/2 bolts (4), tapped plugs (4), UHMW thrust washers (4); 3/8 rod ends (3) + bolts | C55: 1 | D55: lot | E55: 85 | F55: =C55*E55 | G55: 0 | H55: Y
A56: Backrest sockets 1-1/4 x .065 (4) + straps; handle flanges and backing plates | C56: 1 | D56: lot | E56: 60 | F56: =C56*E56 | G56: 0 | H56: Y
A57: Bench clips (4), battery tray + strap, steering pivot base + bushings, engine-guard angle + stays (ladder foot plates: see the footrest line) | C57: 1 | D57: lot | E57: 120 | F57: =C57*E57 | G57: 0 | H57: Y
A58: Bow shelf: aft angle at frame 120, front angle + 3 stringer clips, 4 padeyes + 2 cam straps | B58: Shelf enlarged to x 118.5-140.2 | C58: 1 | D58: lot | E58: 70 | F58: =C58*E58 | G58: 0 | H58: Y
A59: Net weight of the rev 6 cage and layout details (CAD) | B59: Reconciles to the detailed models | C59: 1 | D59: lot | E59: 0 | F59: =C59*E59 | G59: 10.3 | H59: Y
A60: Rev 7: driver station, lights and searchlight, bench, electrical system, deck hardware, safety gear
A61: Driver side frame weldment, 6061 | B61: 2 x 2 x 3/16 sq tube posts, top rail and cross arms (14 ft); 2 x 3 x 3/16 inner rail (3 ft); 1-1/2 x .188 round tube knee braces (rolled to about 19 in radius) and diagonal (8 ft); 3/8 clips; 1/4 base and backing plates | C61: 1 | D61: lot | E61: 340 | F61: =C61*E61 | G61: 23.1 | H61: Y | J61: Bolts to frame x96 and backing plates on the hull side; braces bowed 2.5 in outboard for a large leg; 3/16 walls for the 600 lb hand-hold (Structural Checks)
A62: Console top, skins and dash hood, 5052 | B62: 1/8 in top (13 x 21 in); 0.063 in front and outboard skins; 0.063 in hood (visor, cheeks, arched top) folded and riveted; grommets for the dash loom and bow loom | C62: 1 | D62: lot | E62: 180 | F62: =C62*E62 | G62: 7 | H62: Y | J62: Hood and top screwed with tamper-proof Torx; gauge and switch backs sealed inside
A63: Console fiddle rail, 6061 flat bar 1/8 x 1-1/2 | B63: Raised 1/2 in edge on the aft, inboard and forward edges of the console top (about 29 in); riveted to the cross arms and inner rail; top edges rounded | C63: 1 | D63: lot | E63: 15 | F63: =C63*E63 | G63: 0.5 | H63: Y | J63: Keeps small things from rolling or sliding off, like a galley table
A64: Knee brace pads | B64: 1 in closed-cell foam (minicell) on both braces, UV-treated PU-coated 1000D Cordura or marine vinyl cover, Velcro or laced seam | C64: 2 | D64: ea | E64: 30 | F64: =C64*E64 | G64: 0.3 | H64: Y | J64: Replaceable covers; plain nylon Cordura fades in Florida sun
A65: Life-jacket hook, 316 stainless | B65: J-hook riveted inside the outboard skin, 22 in up, 2.4 in reach | C65: 1 | D65: ea | E65: 12 | F65: =C65*E65 | G65: 0.2 | H65: Y | J65: Keeps a PFD in the sheltered cabinet, clear of the side diagonal
A66: Swamped-boat warning labels | B66: 6 x 4 in UV-laminated marine vinyl, printed from Labels/Swamped_Warning_Label.svg | C66: 3 | D66: ea | E66: 8 | F66: =C66*E66 | G66: 0.05 | H66: N | J66: Helm (console top, by the capacity label) and inside each side of the bench; stability report Finding 1
A67: Cup holder, drop-in, drained | B67: Stainless or nylon, 3.4 in bore, 2.75 in deep (shallow over the thigh) | C67: 1 | D67: ea | E67: 20 | F67: =C67*E67 | G67: 0.3 | H67: Y | J67: Just forward of the grip
A68: Armrest, hinged | B68: Aft 13 in of the 2 x 3 inner rail on a 1/2 in 316 pin through 1/4 in lugs and a U-bracket on the aft cross arm; pad 1/2 in ply, 2 in foam, marine vinyl; detent pin for the up position | C68: 1 | D68: lot | E68: 85 | F68: =C68*E68 | G68: 4.5 | H68: Y | J68: Swings up and aft 95 deg so the driver can get into the seat; rests on the bracket end plate when down
A69: Grip (hand-hold), Hurst T-handle | B69: 1-1/8 in 316 SS rod, cold-drawn (A276 Condition B), bent, welded to a 3 x 2 x 1/4 in 316 base plate; 4 x 1/4 in 316 bolts through the console top and both rail walls with crush tubes, Tef-Gel and a gasket; Hurst 1530040 universal T-handle, polished cast aluminium (new about $62-68, or used on eBay), bar across the boat, threaded straight onto an M16 x 1.5 stud turned on the stick end (no adapter), 316 M16 x 1.5 nylon-insert lock nut under the neck, 1/4 in 316 cross pin | C69: 1 | D69: ea | E69: 140 | F69: =C69*E69 | G69: 2 | H69: Y | J69: Stainless cannot be welded to the 6061 rail; stick and plate sized for 600 lbf; the Hurst handle on its pinned M16 stud is rated 450 lb (Structural_Checks); T-handle position from drv_reach. The Hurst handle is a shift knob: the pin stops a hard sideways pull from unscrewing it. Pull-test the finished grip before use
A70: Transom stiffener, 6061 flat bar 3/8 x 2 in | B70: Vertical, riveted to the transom inside face behind the trim-tab bracket, bottom frame angle to rub rail (15.3 in) | C70: 1 | D70: ea | E70: 15 | F70: =C70*E70 | G70: 1.1 | H70: Y | J70: Carries the tab adjuster pull (about 270 lb) that the bare 1/8 transom cannot
A71: 6061 rectangular tube 2 x 3 x 1/8 in | B71: Forward A-frame crossbar, 3 in deep (24.5 in); bottom on the tie-strut tabs | C71: 1 | D71: ea | E71: 30 | F71: =C71*E71 | G71: 2.8 | H71: Y | J71: Replaces the 1-1/2 in crossbar: fatigue margin for the belt-pull pulses through the tie struts
A72: Dash panel | B72: 1/8 in aluminium, 13.5 in wide, arched 8.5 in top; folds up 66 deg from the console top, faces the driver | C72: 1 | D72: ea | E72: 40 | F72: =C72*E72 | G72: 1 | H72: Y | J72: Tach centre, temp and fuel either side, everything else in the bottom row
A73: 12 V socket and USB-A 5 V / 3 A charger, marine | B73: With hinged rubber flaps; dash bottom row | C73: 1 | D73: set | E73: 40 | F73: =C73*E73 | G73: 0.3 | H73: Y | J73: Both on the hub 20 A outlet circuit
A74: Phone holder, swivel | B74: Ball stalk at the console front-inboard corner, faces the driver; portrait or landscape (con_phone_rot) | C74: 1 | D74: ea | E74: 45 | F74: =C74*E74 | G74: 0.8 | H74: Y
A75: Dash switches | B75: 2 sealed OFF-LO-MED-HI rotary switches (light bar 2-pole, its second pole lights the gauges; searchlight) + sealed NAV-OFF-ANCHOR rocker; DT12 connector | C75: 1 | D75: set | E75: 95 | F75: =C75*E75 | G75: 0.5 | H75: Y | J75: Dash bottom row; the rotaries set the dimmers in the battery bay
A76: Bubble inclinometers | B76: Fore/aft and port/starboard, both on the console top | C76: 2 | D76: ea | E76: 25 | F76: =C76*E76 | G76: 0.6 | H76: Y | J76: For trimming loads
A77: LED light bar 30 in, 180 W, marine | B77: On clamp brackets above the front cage hoop | C77: 1 | D77: ea | E77: 170 | F77: =C77*E77 | G77: 10 | H77: Y | J77: About 13 A
A78: Searchlight 6 in LED + turret, yoke and trunnions | B78: Yaw +-180 deg, pitch +-45 deg; DIY mount | C78: 1 | D78: lot | E78: 200 | F78: =C78*E78 | G78: 9 | H78: Y | J78: About 4 A
A79: Searchlight remote control | B79: Housing, swing handle (pitch), twist grip (yaw) | C79: 1 | D79: lot | E79: 60 | F79: =C79*E79 | G79: 1 | H79: Y | J79: On the console top, forward of the cup holder
A80: Push-pull (choke) cables, 20 ft | B80: Yaw and pitch; zip-tied pair along the hull side and front hoop | C80: 2 | D80: ea | E80: 35 | F80: =C80*E80 | G80: 2 | H80: Y | J80: About 17 ft each installed
A81: Power distribution hub | B81: 12-way sealed blade fuse block with negative bus | C81: 1 | D81: ea | E81: 70 | F81: =C81*E81 | G81: 1 | H81: Y | J81: 9 circuits used, 3 spare; see the wiring schematic
A82: Main battery switch, 1/0-rated (300 A), sealed panel mount | B82: Bench front between the knees, rubber gasket; studs inside the battery bay | C82: 1 | D82: ea | E82: 45 | F82: =C82*E82 | G82: 0.8 | H82: Y | J82: Key for daily use; main switch for battery changes and emergencies
A83: Starter fusible link + MRBF fuses | B83: 4 AWG fusible link at battery +; 60 A MRBF (hub feed) on the switch OUT stud; 10 A MRBF (bilge) at battery + | C83: 1 | D83: lot | E83: 75 | F83: =C83*E83 | G83: 0.4 | H83: Y
A84: Battery cable 1/0 AWG tinned marine | B84: Red 14 ft (battery -> switch -> starter), black 12 ft (battery - -> engine ground); tinned lugs, boots | C84: 1 | D84: lot | E84: 175 | F84: =C84*E84 | G84: 7 | H84: Y | J84: Through the conduit and the 3-hole guard grommet
A85: Cable 6 AWG tinned marine | B85: Red hub feed, black hub return, 4 ft total with lugs | C85: 1 | D85: lot | E85: 25 | F85: =C85*E85 | G85: 0.5 | H85: Y
A86: Duplex 12 AWG red/black tinned marine | B86: Outlet, EFI, start, light bar, searchlight, nav lights; 100 ft | C86: 1 | D86: roll | E86: 165 | F86: =C86*E86 | G86: 6 | H86: Y | J86: No chassis-ground returns
A87: Primary 18 AWG tinned marine, 13 colours | B87: Key, kill, gauges, sensors (tach dark gray, temp tan, fuel pink, trouble brown-white, gauge lights blue-yellow), dimmer and relay signals, bilge, pump; 25 ft spools | C87: 13 | D87: spool | E87: 12 | F87: =C87*E87 | G87: 0.4 | H87: Y | J87: ABYC E-11 colours
A88: Deutsch DT/DTP connector kit | B88: DT12 x3, DT2 x4, DTP2 x7 with pins, seals and wedges; crimp tool | C88: 1 | D88: kit | E88: 240 | F88: =C88*E88 | G88: 0.8 | H88: Y | J88: Every break outside the battery bay
A89: Looms, conduit, glands, grommets | B89: Split loom 5/8 in and 3/8 in; 1-1/2 in sch 40 PVC conduit 3 ft with 3-hole gland caps; 2 PG13 glands; 3-hole guard grommet; aluminium deck cable cover | C89: 1 | D89: lot | E89: 95 | F89: =C89*E89 | G89: 2.5 | H89: Y
A90: Relays and dimmers, sealed | B90: 5 x 12 V 40 A relays (start, EFI main, fuel pump, nav, anchor) + 4 x 1N5408 diodes (2 anchor coil, 2 gauge lights); 2 x IP67 20 A PWM dimmers with 3-wire remote input | C90: 1 | D90: lot | E90: 140 | F90: =C90*E90 | G90: 1.4 | H90: Y | J90: Inside the battery bay
A91: Bilge float switch + AUTO-OFF-MAN switch | B91: Float in the sump; sealed toggle on the bench front | C91: 1 | D91: set | E91: 60 | F91: =C91*E91 | G91: 0.7 | H91: Y | J91: Always on through its own 10 A fuse
A92: Fuel pump and filter, EFI inline | B92: On a bracket on the port engine-bed plate, outside the guard | C92: 1 | D92: set | E92: 170 | F92: =C92*E92 | G92: 2.5 | H92: Y | J92: Delete if the drivetrain list already carries them
A93: Fuel sender, electric 240-33 ohm | B93: In the portable tank, DT2 at the tank front | C93: 1 | D93: ea | E93: 60 | F93: =C93*E93 | G93: 0.4 | H93: Y | J93: The tank must accept a sender
A94: Nav lights | B94: Bow red/green combination on a 12 in stanchion; all-round white on an 18 in mast with U-bolt saddle on the aft hoop | C94: 1 | D94: set | E94: 140 | F94: =C94*E94 | G94: 2.5 | H94: Y | J94: USCG Rule 23 for power vessels under 12 m
A95: Marine plywood 1/2 in, 4x8 | B95: Bench bottom panel, bay bulkhead, both lids | C95: 1 | D95: sheet | E95: 150 | F95: =C95*E95 | G95: 7.5 | H95: Y | J95: Epoxy-coat inside the cooler
A96: Deck hardware | B96: 4 in aluminium cleats (4), 1/4 in bow knees (2), 316 bow-eye strap and 2 in ring | C96: 1 | D96: lot | E96: 110 | F96: =C96*E96 | G96: 4 | H96: Y | J96: Bow cleats on the knees, stern cleats on the transom corners
A97: Fire extinguisher, USCG B-1 (5-B:C) marine | B97: With quick-release bracket | C97: 1 | D97: ea | E97: 40 | F97: =C97*E97 | G97: 4.5 | H97: Y | J97: Bow shelf, starboard of the tank
A98: Air horn, 8 oz can | B98: With bracket | C98: 1 | D98: ea | E98: 25 | F98: =C98*E98 | G98: 0.8 | H98: Y | J98: Bow shelf, port of the tank
A99: Flag staff and international-orange flag | B99: 3/4 in 6061 tube removable staff in a 7/8 in socket on a U-bolt saddle on the aft hoop, 12 in port of the stern light; 12 x 10 in nylon flag, bottom edge 122 in above the hull bottom | C99: 1 | D99: lot | E99: 45 | F99: =C99*E99 | G99: 1 | H99: Y | J99: Florida Statute 327.391: flag at least 10 x 12 in, at least 10 ft above the lowest part of the boat; pull the staff to trailer
A100: Rev 7 fasteners | B100: SS bolts, rivnuts, U-bolts and clamps for the items above | C100: 1 | D100: lot | E100: 60 | F100: =C100*E100 | G100: 2 | H100: N
A102: Total | F102: =SUM(F5:F100) | G102: =SUM(G5:G100)
...
